geanno/Annotator.py
geanno/__init__.py
geanno-0.9.2.dist-info/LICENSE
geanno-0.9.2.dist-info/METADATA
geanno-0.9.2.dist-info/WHEEL
geanno-0.9.2.dist-info/top_level.txt
geanno-0.9.2.dist-info/RECORD
