Metadata-Version: 2.1
Name: geanno
Version: 0.9.2
Summary: A python package for annotation of genomic elements
Home-page: https://geanno.readthedocs.io/en/latest/
Author: Matthias Bieg
Author-email: matthias.bieg@gmail.com
License: UNKNOWN
Platform: UNKNOWN
Classifier: Programming Language :: Python :: 3
Classifier: License :: OSI Approved :: BSD License
Classifier: Operating System :: OS Independent
Requires-Python: >=3.0
